{
  "spec": "btc",
  "deposit": 200.0,
  "period": {
    "date_from": "2024.06.01",
    "date_to": "2026.05.31",
    "days": 729
  },
  "metrics": {
    "monthly": {
      "month_count": 24,
      "total_profit": 7837.250000000001,
      "total_return": 39.18625,
      "profitable_months": 20,
      "loss_months": 4,
      "big_loss_months": 1,
      "strong_months": 6,
      "trend_months": 3,
      "median_monthly_return": 0.09455596577392997,
      "top3_concentration": 0.5480353440301126,
      "top5_concentration": 0.7250821397811731,
      "total_trades": 122,
      "max_loss_vs_initial": 1.4648500000000002
    },
    "continuous": {
      "final_balance": 8037.222800000009,
      "net_profit": 7837.222800000009,
      "net_return": 39.186114000000046,
      "profit_factor": 2.8831967732099186,
      "max_drawdown_abs": 773.0114999999832,
      "max_drawdown_pct": 0.28295378129341314,
      "recovery_factor": 10.138559128810087,
      "avg_win": 272.7018590909093,
      "avg_loss": 56.238635135135105,
      "avg_win_loss": 4.849012754943954,
      "monthly_returns": [
        0.1613324999999968,
        1.4013105635121728,
        0.026880074012450385,
        0.14433486132009904,
        0.21634401481838644,
        -0.06406367933137307,
        0.2595215186341233,
        0.43352486134464296,
        -0.2174690197931028,
        -0.017425447704600708,
        0.4215446805589795,
        0.009658614979834723,
        0.7081203925229641,
        0.18292441421968322,
        0.6163788869141548,
        0.01503401017717875,
        -0.003565807070531427,
        0.1879501373168213,
        0.23838235426958837,
        0.03853632068038066,
        0.01573870580379464,
        0.04477056053769472,
        0.008576212251207622,
        0.0008025748440908669
      ],
      "sharpe": 2.125015316193147,
      "sortino": 15.015988187676149,
      "calmar": 18.926523191038587,
      "trade_count": 118
    },
    "r_metrics": {
      "has_r_metrics": true,
      "big_win_ratio": 0.20454545454545456,
      "micro_win_ratio": 0.29545454545454547
    }
  },
  "hard_gates": {
    "24月盈利月数": false,
    "亏损月数量": false,
    "大亏月": false,
    "单月亏损绝对保护": false,
    "月收益中位数": true,
    "强利润月数量": true,
    "大趋势月数量": true,
    "Top3集中度": true,
    "Top5集中度": true,
    "720d最大回撤": false,
    "720dRecovery": true,
    "720dPF": true,
    "Sharpe": true,
    "Sortino": true,
    "Calmar": true,
    "avg_W/|avg_L|": true,
    ">3R大赢单占比": true,
    "<0.5R微利单占比": true
  },
  "hard_failures": [
    "24月盈利月数",
    "亏损月数量",
    "大亏月",
    "单月亏损绝对保护",
    "720d最大回撤"
  ],
  "score": {
    "modules": {
      "稳定性": 13.4697868087233,
      "利润能力": 30.0,
      "风险质量": 20.672903012247076,
      "趋势利润结构": 11.454545454545455
    },
    "total_score": 75.59723527551583,
    "top_drags": [
      "稳定性/亏损月控制",
      "稳定性/24月盈利月数",
      "风险质量/720d回撤"
    ]
  },
  "grade": "淘汰"
}